{
  "id": "template-eventos-indaia-completo",
  "nome": "Modelo Completo - Eventos Indaiá",
  "descricao": "Template completo para contratos de eventos (todas as cláusulas)",
  "conteudo": "1) OBJETO:\n\nÉ objeto deste contrato a prestação de serviços na realização do evento de {{TIPO_EVENTO}}, que contará com o serviço de: {{SERVICOS}} que ocorrerá no dia {{DATA_EVENTO}} com um número de {{NUM_CONVIDADOS}} adultos no espaço {{ESPACO}}\n\n2) ALIMENTOS:\n\na) O cardápio do evento será necessariamente escolhido dentre as opções de menus disponibilizados pelo CONTRATADO. Eventual alteração do cardápio ora escolhido só será permitida mediante aceite do CONTRATADO, que se perfectibilizará por meio de aditivo contratual firmado por ambas as partes. Parágrafo Único: Em caso de alteração do cardápio e/ou aumento no número de pessoas por força de aditivo contratual, observar-se-á o valor vigente do cardápio escolhido no ato da assinatura do aditivo, que poderá ser diverso do valor descrito no presente contrato, eis que o cardápio está sujeito a atualização de preços.\n\nb) Na confirmação final do evento, realizada até 30 dias anteriores à realização do evento, o CONTRATANTE deverá fornecer, formalmente e por escrito o número de pessoas que comparecerão ao evento. Conta-se no número de pessoas: contratantes, convidados adultos, crianças pagantes (a partir de 7 anos) e fornecedores terceirizados. Parágrafo Primeiro: Caso o número de pessoas confirmadas no prazo estipulado no Caput desta Cláusula seja superior ao inicialmente previsto não incidirá multa relativa a tal acréscimo de convidados, sendo liberado o aumento de participantes do evento conforme a capacidade do ambiente escolhido mediante aditivo contratual previamente assinado entre as partes. Para os convidados adicionais, será aplicado o valor do cardápio vigente na data do aditivo contratual. Parágrafo Segundo: No caso de haver excedentes de pessoas no dia da realização do evento, não será tolerado pessoas excedentes sem cobrança de multa. Desta forma será cobrado no relatório de consumo o valor por pessoa que incidirá em multa de 150% do valor vigente na data da realização (buffet + bebida + custo com a equipe) por pessoa. Parágrafo Terceiro: Em caso de comparecimento ao evento de número menor de convidados do que o efetivamente confirmado, será cobrado valor integral do evento, considerando o informado na confirmação final. Parágrafo Quarto: A contagem do número de convidados é realizada no decorrer do evento e descrita em relatório apresentado à cerimonialista ou contratantes e, após assinatura do referido relatório pelos mesmos, o número contabilizado se torna indiscutível. Parágrafo Quinto: Em caso de não cumprimento do prazo de 30 dias antecedentes ao evento, fica estipulada uma multa ao contratante de R$2.000,00. Parágrafo Sexto: Para realizar qualquer modificação no evento, é necessário efetuar as alterações ou inclusões com, no máximo, 7 dias de antecedência em relação à data da realização do mesmo. Após esse prazo, não será possível realizar qualquer tipo de alteração.\n\nc) A escolha dos itens contratados no Cardápio, deve ser confirmada em até 30 dias antes da realização do evento. Passado o referido prazo fica convencionado que a CONTRATADA irá escolher as opções padrões do buffet assinalado na cláusula 2 item B, deste instrumento\n\nd) É vedado levar ao evento qualquer alimento ou bebida sem prévia autorização do CONTRATADO, com exceção de bolos de casamentos ou docinhos de festas. Parágrafo Primeiro: O descumprimento do descrito no caput desta Cláusula sujeitará o CONTRATANTE a cobrança de taxas não previstas neste instrumento. Parágrafo Segundo: É facultado ao CONTRATADO a permissão do uso de suas dependências operacionais (Cozinha, Almoxarifado, Estoques e outros ambientes similares). Em caso de liberação do uso da cozinha, é aplicada a taxa mínima de R$ 8.500,00.Parágrafo Terceiro: No caso em que o CONTRATANTE opte por terceirizar os serviços de CAFÉ ou LANCHES E ALIMENTOS DE QUALQUER NATUREZA, o CONTRATADO não será responsável por fornecer quaisquer utensílios ou permitir a utilização de sua cozinha para a realização desses serviços. Para a terceirização do serviço de CAFÉ, será cobrada uma taxa no valor de R$250,00. E para a terceirização de LANCHES e ALIMENTOS (mesa de frios ou alimentos de qualquer natureza) será cobrada uma taxa no valor de R$1.000,00.\n\ne) O horário do serviço de alimentação estará estipulado na Ordem de Serviço do evento, que será enviada ao CONTRATANTE. Se o atraso no serviço de alimentos ocorrer por culpa da (o) CONTRATANTE fica estipulada multa de R$ 1.000,00 por hora de atraso. Parágrafo Primeiro: A CONTRATADA adverte sobre a necessidade do cumprimento do horário estipulado por conta da segurança alimentar e qualidade do cardápio servido. Parágrafo Segundo: O serviço de buffet contemplado por este contrato prevê a montagem de apenas 01 (uma) ilha de buffet. Caso o CONTRATANTE tenha interesse na montagem de outra ilha de serviços haverá custo adicional de R$ 2.000,00, mediante prévia aprovação por parte do CONTRATADO para liberação do serviço. Parágrafo Terceiro: O serviço de buffet/coquetel ficará disponível por no máximo 2 (duas) horas durante o evento.\n\nf) Todos os prestadores de serviços terceirizados por parte do CONTRATANTE serão considerados como comensais do serviço de alimentação e bebidas. Não será servido cardápio diverso para convidados e prestadores de serviço. Parágrafo Único: O valor cobrado por prestador de serviço será o valor do cardápio escolhido para o evento decrescido de R$15,00, caso a opção de bebida seja OPEN BAR será cobrado o valor do OPEN BAR 01 (Sem Bebidas Alcoólicas), a menos que a contratação do OPEN BAR 5 ou 6 seja realizada, nesse caso, a cobrança equivalerá a 60% do valor. Na opção de CONSUMAÇÃO, será cobrado o valor das bebidas consumidas.\n\ng) Crianças com idade entre 7 a 12 anos pagam 50% do valor do cardápio escolhido, crianças de 0 a 6 anos são isentas.\n\nh) O CONTRATADO não oferece degustações de cardápios, entretanto, em havendo interesse pelo CONTRATANTE, poderá ser solicitada disponibilidade para a realização da degustação, no valor mínimo de R$ 300/pessoa para degustação de 6 opções do cardápio de acordo com a disponibilidade de data e horários do CONTRATADO. Valores de degustação sujeitos a mudança/atualização sem prévio aviso. Parágrafo Primeiro: O valor, dia e horário, serão formalizados via aditivo contratual, e caso o CONTRATANTE não compareça na data agendada, não será possibilitado o reembolso, nem a utilização do valor como crédito.\n\ni) Fica expressamente proibido ao CONTRATANTE o transporte ou armazenamento dos alimentos servidos pelo CONTRATANDO. Paragráfo primeiro: Em caso de descumprimento desta cláusula, o CONTRATANTE ficará sujeito ao pagamento de multa no valor de R$ 5.000,00 (cinco mil reais), sem prejuízo de outras sanções cabíveis. Paragráfo segundo: O CONTRATADO não se responsabiliza por qualquer dano, mal-estar, intoxicação ou problema de saúde que venha a ocorrer com o CONTRATANTE ou terceiros em decorrência do transporte ou armazenamento inadequado dos alimentos. Paragráfo Terceiro: O CONTRATANTE declara estar ciente de que o transporte e armazenamento inadequados dos alimentos podem comprometer sua integridade e segurança, assumindo integralmente os riscos e responsabilidades decorrentes de tal prática.\n\nj) O número mínimo para contratação de buffet é de 30 convidados adultos. Caso se concretize um número inferior na confirmação final do evento, será mantido e cobrado o valor para a quantidade mínima estipulada em contrato.\n\nk) Caso no dia do evento exceda um número de convidados superior a 20% do estipulado na confirmação final, o contratante deverá realizar uma caução de 50% do valor destes excedentes com as devidas multas, ainda durante o evento, em caso de não cumprimento a parte contratada poderá suspender o serviço de alimentação e bebida.\n\n3) BEBIDAS:\n\na) Eventos contratados na modalidade consumação, observar-se-á o valor vigente das opções escolhidas no ato da confirmação final do evento, onde é realizada a escolha do cardápio. Parágrafo Único: Os valores podem ser diversos dos descritos no presente contrato, eis que o cardápio está sujeito a atualização de preços.\n\nb) O fornecimento de bebidas do serviço de Open-bar encerrará ao final do horário previsto para finalização do evento, que terá duração de oito horas. Parágrafo Único: Excedendo o prazo previsto no caput desta cláusula, o adicional cobrado por hora estendida será de R$ 1.000,00 (Um mil reais). Não excluindo outros valores cobrados por hora adicional, como por exemplo a hora adicional de open-bar (cláusula 7. e).\n\nc) É expressamente proibido o consumo de bebidas alcoólicas por menores de idade nas dependências do estabelecimento do CONTRATADO, razão pela qual o CONTRATADO não se responsabiliza por eventual consumo das mesmas por menores de idade, sendo estes de absoluta responsabilidade dos seus responsáveis legais.\n\nd) A contratação de bartender terceirizado pelo CONTRATANTE depende de prévia autorização do CONTRATADO e do pagamento de taxa de R$700,00. Valores podem sofrer mudança ou atualização sem prévio aviso. O CONTRATADO não fornece e não se responsabiliza por disponibilizar gelo, bebidas e utensílios para uso exclusivo do bartender. É possível contratação de gelo para serviços terceirizados do evento via aditivo contratual - mediante disponibilidade do CONTRATADO.\n\ne) Havendo a contratação do Open Bar de Drinks, o CONTRATADO dispõe de um serviço que ficará disponível para os seus convidados durante um determinado número de horas contratadas. Em caso de contratação de 5 horas de serviço, começará a ser servido a partir do encerramento do serviço de Buffet; Caso os contratantes optem por ALTERAR o horário de início dos drinks, será cobrado o acréscimo de R$10,00/pessoa para que a alteração seja feita. E em caso de contratação de 8 horas de serviço, começará a ser servido a partir do término da Cerimônia de Casamento. Parágrafo Primeiro: Não é autorizada a customização ou troca dos drinks. Parágrafo Segundo: A marca utilizada para bebidas será conforme a preferência do CONTRATADO. Parágrafo Terceiro: Não será autorizado a utilização de outros copos/taças para esse open bar, só serão aceitos os utensílios selecionados pelo CONTRATADO. Parágrafo Quarto: O serviço será exclusivo para atendimento volante, dessa forma não contará com estrutura de bar e barman. Parágrafo Quinto: Em caso de quebra de taças de vidro ou cobre utilizadas neste open bar, terá um custo de 45 reais por quebra. Parágrafo Sexto: O CONTRATADO irá fornecer taças de vidro e cobre, semelhante as fotos de referência, ou seja, não necessariamente o copo será o mesmo da foto. Parágrafo Sétimo: Na falta de ingredientes frescos para o preparo de determinados drinks, é possível a troca de até 02 drinks da listagem por outros similares. Parágrafo Oitavo: Caso o número de convidados do CONTRATANTE for inferior a 30 convidados, será cobrado o valor para 30 convidados. Parágrafo Nono: A contratação do Open Bar de Drinks com Álcool e sem Álcool é permitida a partir da consumação.\n\nf) Crianças com idade entre 0 a 6 anos são isentas, crianças de 7 a 12 anos pagam 50% do valor do serviço de OPEN BAR 01 (Sem bebidas alcoólicas), fornecedores seguem conforme estipulado na cláusula 2) f), e os demais convidados pagam o valor integral do Open Bar contratado.\n\ng) No serviço de rolha (bebidas trazidas pelo CONTRATANTE), será cobrada uma taxa por abertura de garrafa, e não pelo consumo do líquido. Será permitida rolha de quaisquer bebidas, mediante prévia autorização expressa do CONTRATADO e conforme os preços estipulados pelo mesmo. O prazo para o CONTRATANTE definir se trará rolha e quais bebidas serão trazidas deverá seguir o estipulado na cláusula 2) c), e os valores seguirão conforme previsto na cláusula 3) a). Parágrafo Primeiro: A cobrança pela rolha será realizada apenas após a realização do evento, não sendo cobrado nenhum valor de forma antecipada. Parágrafo Segundo: Para garrafas com volume superior a 750 ml, o valor da rolha será cobrado proporcionalmente à quantidade de bebida contida na garrafa. Exemplo: Uma garrafa de destilado de 3 litros, corresponderá a 4 rolhas. Parágrafo Terceiro: Será cobrada uma taxa fixa no valor de R$2.500,00 para o caso de o CONTRATANTE optar por trazer todas as bebidas do evento (refrigerantes, água, sucos, cervejas). Parágrafo Quarto: O serviço de atendimento (garçom) não está incluído na referida taxa de R$2.500,00. O valor adicional referente ao serviço de garçom será repassado de acordo com a tarifa vigente na data da solicitação.\n\nh) O serviço de OPEN BAR é servido em jarras ou garrafas de litro (cervejas). Não aplicável para o Open bar de Drinks, onde os drinks são servidos em copos e taças disponibilizadas exclusivamente para esse serviço. Parágrafo Único: É autorizado apenas uma opção de cada marca de bebida no open bar, portanto, não é permitido dois tipos de bebidas iguais (marcas diversas da mesma bebida) no mesmo evento, com exceção do soft drink (água e refrigerante). Consulte preços diferenciados para o serviço de Open Bar com garrafas e/ou latas.\n\ni) Findo o evento, os contratantes e/ou responsável pelo evento farão a contagem e confirmação das bebidas consumidas, quando for o caso, ou das rolhas utilizadas, devendo firmar termo de consumo, o qual fará parte integrante deste instrumento, servindo como título executivo em caso de inadimplemento. Parágrafo Único: O pagamento das bebidas consumidas será realizado no final do evento, aferindo-se o respectivo consumo e pendências gerais. A penalidade para o atraso no pagamento é de 10% (dez por cento) do valor do saldo de consumo e pendências dos eventos.\n\nj) O número mínimo para contratação de OPEN BAR é de 30 pessoas. Caso se concretize um número inferior na confirmação será mantido o mínimo de 30 pessoas.\n\nk) Havendo a contratação do Open Caipirinha, o CONTRATADO dispõe de 5 opções de sabores: vinho, morango, tropical, limão e framboesa, nas opções com e sem álcool, em um serviço volante, que ficará disponível para os seus convidados durante 8 horas. O consumo das caipirinhas inicia no momento da recepção (após a cerimônia). Parágrafo Primeiro: Não é autorizada a customização ou troca dos drinks. Parágrafo Segundo: A marca utilizada para bebidas será conforme a preferência do CONTRATADO. Parágrafo Terceiro: Não será autorizado a utilização de outros copos/taças para esse open bar, só serão aceitos os utensílios selecionados pelo CONTRATADO. Parágrafo Quarto: O serviço será exclusivo para atendimento volante, dessa forma não contará com estrutura de bar e barman. Parágrafo Quinto: Em caso de quebra do copo utilizado neste open bar, terá um custo de 45 reais por quebra. Parágrafo Sexto: O CONTRATADO irá fornecer copo de vidro (estilo copo conserva), semelhante as fotos de referência, ou seja, não necessariamente o copo será o mesmo da foto. Parágrafo Sétimo: Na falta de ingredientes frescos para o preparo de determinados drinks, é possível a troca de até 02 drinks da listagem por outros similares.\n\n4) DECORAÇÃO:\n\na) Não será restituído qualquer valor do pacote de decoração contratado pela não utilização de alguns itens e não é autorizada a troca das peças decorativas, devido ser um pacote promocional, salvo itens adicionais contratados. Parágrafo Único: Caso o contratante não possua decorador e queira que os itens de decoração inclusos em contrato sejam montados pela nossa equipe, deverá ser cobrada uma taxa de R$ 3.000,00 para este serviço. Caso o contratante não tenha decorador e queira se responsabilizar pela montagem dos itens essa taxa não será cobrada.\n\n5) MATERIAIS:\n\na) Fica o CONTRATADO responsável pelo fornecimento dos materiais: mesas redondas para sentar convidados, mesa para o buffet, guardanapos de tecidos, réchaud, talheres, copos de vidro, taças de vinhos e taças de espumantes, pratos e pratos de sobremesa. Sendo estas as únicas mobílias e acessórios disponibilizados pelo CONTRATADO, sendo assim esses itens equivalem a 70% do valor total como locação, será gerado fatura de locação conforme Lei Complementar 116/03, as atividades de locação de máquinas e equipamentos e de quaisquer outros bens móveis não constitui fato gerador do ISSQN e portanto não está sujeita a emissão de Nota Fiscal de Serviços, poderá ser emitida fatura de aluguel pela empresa AGG Holding Locações (38.542.472/0001-49). Está incluso em contrato a locação do salão interno,exceto área kids, em caso do contratante optar por contratar a área externa, ou a área kids, deverá ser observado o valor vigente na data desta contratação.\n\nb) É responsabilidade do CONTRATADO a disponibilização, para uso exclusivo no momento e local da cerimônia, de no máximo 100 cadeiras na cor branca e material de ferro, sem custo adicional. Parágrafo Único: Caso o CONTRATANTE tenha um número maior de convidados, não será disponibilizada uma quantia maior de cadeiras, diverso das cadeiras do jantar. Para a recepção (local do jantar), o CONTRATADO dispõe de cadeiras de madeira para locação.\n\nc) Fica o CONTRATANTE responsável por todos os danos e furtos causados pelos participantes ou fornecedores contratados do evento nas instalações, móveis e no próprio imóvel locado, danos esses que deverão ser devidamente indenizados, visando à recomposição dos bens danificados, de forma a manter as suas condições e características originais. Copos/Taças/Pratos têm valor R$ 25,00 (vinte e cinco reais) por quebra, salvo disposição específica conforme cláusula 3) e). Demais itens terão seus valores apurados em caso de quebra e/ou danos por parte do CONTRATADO.\n\n6) SERVIÇOS:\n\na) Haverá cobrança de 15% (Taxa de Equipe) do valor total do cardápio e consumo de bebidas a título de prestação de serviços de garçons e barmans. A taxa de equipe é cobrada em todos os serviços adicionais (aditivos contratuais) e relatório de consumo final. Em contrato temos a cobrança da taxa de equipe referente aos convidados negociados até então, caso posteriormente, seja adicionado um número maior de pessoas, deverá ser cobrado proporcionalmente em cima dos convidados e fornecedores adicionais. Em caso de serviço de bebidas por consumação, a taxa de equipe será cobrada no relatório final junto com o consumo das bebidas após o evento.\n\nb) É responsabilidade do CONTRATANTE toda e qualquer lesão corporal ou moral gerada ou estimulada pelos participantes do evento - por este motivo a importância de um segurança profissional ser contratado pelo organizador do evento em eventos com consumo de bebidas alcoólicas. Ressaltamos a necessidade da contratação de um profissional no assunto, é garantia na tranquilidade e sucesso de seu evento. Uma atitude preventiva que pode gerar economia em possíveis depredações e ostensividade para evitar acontecimento de conflitos entre convidados. Saiba escolher empresas que tomam atitudes preventivas quanto às possibilidades de ocorrências negativas em seu evento, prezamos por boas práticas. A contratação deste profissional pode ocorrer por intermédio do CONTRATADO, sem que haja responsabilidade sobre este fornecedor.\n\nc) O CONTRATADO informa que o horário de atendimento do pós-vendas é de Segunda a Sexta-feira das 09:00 às 12:00 / 13:00 às 17:00 horas. Parágrafo Primeiro: Para agendar uma visita no ambiente contratado, será necessário realizar um agendamento prévio com no mínimo de 48 horas de antecedência, sujeito a aprovação conforme disponibilidade de horários. Parágrafo Segundo: As visitas poderão ocorrer de segunda a quinta-feira das 09:00 às 12:00 / 13:00 às 17:00 horas.\n\nd) Para orientações sobre o serviço de fornecedores terceirizados o CONTRATADO disponibiliza um Manual de Orientações através deste link: https://eventosindaia.com.br/manual-eventos. Parágrafo Único: Fica estipulada a obrigatoriedade do cumprimento das boas práticas transcritas neste manual, sob pena de não realização do evento ou cancelamento por justa-causa. É responsabilidade do CONTRATANTE garantir que fornecedores terceirizados cumpram com normas de segurança, manutenção e bom-uso das dependências do CONTRATADO transcritas no manual citado.\n\ne) É realizada a cobrança da taxa de estacionamento devido a disponibilidade de monitoramento do espaço e segurança.\n\nf) No caso de contratação de área externa pelo CONTRATANTE junto ao CONTRATADO, como por exemplo Cerimônia na Praia ou qualquer outra cerimônia ao ar livre, estará sujeito à cobrança de valores adicionais. O CONTRATADO será responsável pela obtenção de todas as autorizações necessárias, incluindo alvarás e liberações, para a realização da cerimônia. Parágrafo Primeiro: O serviço de cerimônia externa estará sujeito à aprovação do órgão municipal ou federal responsável. Em caso de negação da aprovação, o CONTRATADO será obrigado a reverter o valor do serviço contratado em créditos para uso no evento principal, conforme descrito na Cláusula 8-g, descontados todos os custos já incorridos para a obtenção de documentos ou contratações necessárias. Parágrafo Segundo: O CONTRATANTE poderá cancelar o serviço de cerimônia externa até trinta dias antes da realização do evento. Neste caso, o valor pago pelo CONTRATANTE será revertido em créditos para uso no evento principal, conforme descrito na Cláusula 8-g, descontados todos os custos já incorridos para a obtenção de documentos ou contratações necessárias. Parágrafo Terceiro: Nos ambientes que possuam espaço externo, a CERIMÔNIA AO AR LIVRE somente poderá ser realizada mediante a contratação adicional desse serviço. O espaço externo poderá ser utilizado para outros fins sem custo adicional.\n\ng) Em caso de contratação dos serviços de Hospedagem para os ambientes de Nova Veneza, ficam estipuladas as regras do serviço: Parágrafo Primeiro: A capacidade máxima do estabelecimento é de 16 (dezesseis) pessoas. Este limite deve ser rigorosamente respeitado para garantir o conforto e a segurança de todos os hóspedes. Parágrafo Segundo: O horário de check-in estará disponível a partir das 15h. É imprescindível que os hóspedes respeitem este horário para assegurar que o quarto esteja devidamente preparado para a estadia. Qualquer chegada antecipada estará sujeita à disponibilidade e poderá incorrer em taxas adicionais. Parágrafo Terceiro: O check-out deve ser realizado até às 10h. Os hóspedes devem cumprir rigorosamente o horário de check-out para permitir a preparação adequada do espaço para os próximos visitantes. O descumprimento deste horário poderá resultar na cobrança de uma taxa adicional. Parágrafo Quarto: O café da manhã será servido das 8h às 10h. É solicitado que os hóspedes respeitem este horário para garantir que possam desfrutar de todas as opções disponíveis. Parágrafo Quinto: Para pacotes que incluírem o serviço de Open Food e Bar, o horário de atendimento para alimentação e bebidas será das 15h até o início do evento programado. Os hóspedes devem planejar suas refeições dentro deste intervalo de tempo para garantir o melhor aproveitamento do serviço oferecido.\n\n7) RESPONSABILIDADES:\n\na) Não será de responsabilidade do CONTRATADO: I) decoração do espaço de eventos (com exceção para colocação dos itens de decoração em pacotes específicos oferecidos e comercializados pelo CONTRATADO, quando adquirido tal serviço pelo CONTRATANTE); II) equipamentos de SOM / DJ; III) carga e descarga de materiais e equipamentos para os eventos; IV) falta de energia elétrica geral durante a realização do evento, decorrente da ausência de fornecimento pela concessionária; V) montagem do Layout de mesas sem que o croqui seja enviado com no mínimo 15 dias de antecedência.\n\nb) É obrigatória a contratação, diretamente com o CONTRATADO ou de forma terceirizada, de um gerador de energia elétrica. O valor da taxa para a utilização do gerador será estipulado na assinatura do contrato. Em caso de falta da contratação terceirizada do gerador, o contratante concorda em pagar uma multa no valor de R$2.000,00 por quebra de contrato. Nos casos de eventos promocionais do tipo \"Dinner\" e \"Elopement\", isentos de cobrança de gerador, a multa não se aplica. Em situações onde não houve a contratação do gerador em caso de falta de energia, o contratante concorda em efetuar um pagamento adiantado de R$4.000,00 para possibilitar a ativação do gerador. A utilização do gerador será disponibilizada até que o fornecimento de energia seja restabelecido, sem cobrança adicional pelo tempo de utilização, com um prazo máximo de até 30 minutos para ligar o gerador. Qualquer dano causado ao equipamento do CONTRATADO devido a descargas elétricas na rede pública será de responsabilidade das concessionárias, permissionárias ou sob qualquer outra forma de empreendimento, conforme regulamentado pela Agência Nacional de Energia Elétrica - ANEEL e CF (§ 6º do art. 37). Estas entidades terão responsabilidade direta e objetiva sobre danos causados moralmente e civilmente em tais casos.\n\nc) É de responsabilidade do CONTRATANTE: A orientação aos prestadores de serviço terceirizados, a exemplo de fornecedores de serviços de decoração, sistema de sonorização, entre outros, de que podem ocupar o espaço destinado aos seus serviços a partir das 09:00h do dia do evento e garantir que estes mesmos fornecedores terceirizados removam todo seu material ou equipamentos até às 09:00h do dia seguinte ao evento, exceto equipamentos de sonorização, que deverão ser retirados impreterivelmente ao final do evento, sendo acompanhados por um profissional da CONTRATADA. Parágrafo Primeiro: Garantir que, quando houver evento na agenda do CONTRATADO no dia seguinte e no mesmo ambiente de realização do evento do CONTRATANTE, os equipamentos dos prestadores de serviços terceirizados sejam retirados obrigatoriamente ao final do evento, sendo acompanhados por um profissional da CONTRATADA. Parágrafo Segundo: Garantir que o sistema de ar condicionado tenha sua utilização iniciada a partir de duas (02) horas que antecedem ao horário de início do evento. Parágrafo Terceiro: Garantir que passagens de som/instalação de equipamentos de som respeitem os horários do restaurante ou demais eventos que estejam sendo realizados no espaço do CONTRATADO, sob pena de multa de R$ 1.000,00 (um mil reais) pelo seu descumprimento.\n\nd) Os objetos de decoração e outros itens, tais como alimentos, doces, tortas, etc., que não são fornecidos pelo CONTRATADO, não incidirão qualquer responsabilidade pela sua manutenção e cuidados.\n\ne) Respeitar o tempo de duração máxima para o evento, de 8 horas consecutivas, ajustando-se desde já 01 hora adicional sem custo extra para eventos de casamento com cerimônia no local, restando pactuado, por fim, que a hora excedente sofrerá acréscimo do valor de R$ 1.500,00/hora. Não excluindo outros valores cobrados por hora adicional, como por exemplo a hora adicional de open-bar (cláusula 3. b).\n\nf) O CONTRATADO não se responsabiliza por quaisquer itens deixados no espaço de evento pelo CONTRATANTE, não havendo garantia de que todos ambientes estejam monitorados por câmeras de vídeo. Parágrafo único: É de responsabilidade do CONTRATANTE a vistoria no local, após a finalização do evento, a fim de verificar se foi esquecido algo no local.\n\ng) O CONTRATANTE deverá estar ciente, bem como seus fornecedores por si contratados, de que nenhuma retribuição e/ou comissionamento é devido aos funcionários e colaboradores, estando expressamente proibida a sua prática. Parágrafo Primeiro: O CONTRATADO disponibiliza uma lista de fornecedores para serviços terceirizados e não exige a obrigatoriedade da contratação, dessa forma não possui nenhuma responsabilidade pelos serviços prestados por terceiros. Parágrafo Segundo: Por parte do CONTRATADO, não há restrições referente aos fornecedores terceirizados, o CONTRATANTE poderá optar pelo fornecedor de sua preferência.\n\nh) As partes declaram que a cerimonialista tem caráter de responsável legal do CONTRATANTE durante todo o evento. Parágrafo Único: A cerimonialista sempre que solicitada pelo representante da CONTRATADA, referente a questões financeiras, deverá prestar o devido suporte. O documento do(a) cerimonialista que estará presente no dia do evento, deverá ser encaminhado para a CONTRATADA, junto com as definições finais do evento, que serão solicitadas pela equipe de atendimento do CONTRATANTE.. A contratação de uma Cerimonial, é imprescindível para o sucesso do evento.\n\ni) Não é autorizado banda (fora dos parâmetros previstos no manual de eventos), e no equipamento do DJ, não é autorizado a utilização de subwoofer. A posição da estrutura de som e buffet no layout do salão, não é possível ser alterada. Fica estipulado o limite de decibéis conforme abaixo: Esp. Cristal: 90 decibéis até as 23:00 | 80 decibéis até 04:00. A multa pelo não cumprimento é de R$1.500,00/hora. É de inteira responsabilidade do organizador do evento cumprir o limite de decibéis estipulado. O CONTRATADO se responsabiliza por apresentar, durante a realização do evento, valores através de um medidor de decibéis, a medição é feita nas proximidades da origem sonora. Usamos tais patamares para evitar que seu evento seja interrompido pela Municipalidade. Todos os patamares estipulados são de volumes de som considerados altos e coerentes com eventos de festa. Em caso de descumprimento dos decibéis permitidos, fica a critério do contratado a interrupção do evento e aplicação de multa por não cumprimento da regra por parte do contratante.\n\nj) Toda e qualquer tratativa e disposição acerca do evento deve estar disposta em contrato ou em seus aditivos e anexos. Não serão consideradas conversas ou diálogos diretos com vendedores acerca da realização e operação do evento, salvo os acordos financeiros realizados dos números oficiais do setor de Pós Vendas do Indaiá: (47) 98854-4227 / (47) 99668-4262 via aplicativo WhatsApp. O Prazo de retorno é de até 24 horas úteis após o envio da última mensagem.\n\nk) É de extrema importância que as capacidades definidas pelo setor de pós-vendas sejam rigorosamente respeitadas, a fim de garantir a aderência aos padrões de segurança e conforto estabelecidos. O CONTRATADO não será responsável por qualquer eventual superlotação do ambiente, uma vez que a definição das capacidades de atendimento cabe exclusivamente ao setor de pós-vendas da CONTRATADA. A total responsabilidade de assegurar o estrito cumprimento das capacidades estabelecidas nos layouts padronizados recai sobre o CONTRATANTE, evitando qualquer forma de excedente que possa comprometer a segurança e a experiência adequada dos participantes.\n\nl) É de responsabilidade do CONTRATANTE não permitir acesso de pessoas não convidadas ao evento. Desta forma, todas as pessoas presentes serão contabilizadas como convidados/comensais do evento.\n\nm) Pode o CONTRATADO, substituir o espaço de realização do evento, por motivos de força maior, disponibilizando assim ao CONTRATANTE, outras opções de ambientes para a realização do evento.\n\nn) É responsabilidade do CONTRATANTE verificar o conteúdo da Ordem de Serviço antes da realização do evento. Em caso de divergência, é responsabilidade da CONTRATANTE comunicar a falta ou divergência de informação. O CONTRATADO se compromete a encaminhar a Ordem de Serviço com no mínimo 48 horas de antecedência ao evento.\n\no) As partes declaram estar cientes que o presente contrato foi livremente negociado, sendo o valor total do presente resultado de diversos fatores internos e externos, tais como contratação mediante pacotes promocionais vigentes, forma de pagamento, sazonalidade – época da contratação e data do evento – não produzindo, portanto, qualquer efeito vinculante perante terceiros, sendo que os termos ora negociados não se aplicarão por analogia a outros contratantes.\n\np) As partes reconhecem que este contrato se trata de instrumento personalíssimo e suas disposições não se aplicarão a qualquer outro contrato firmado pela CONTRATADA com terceiros e, de mesmo modo, as disposições firmadas para com outros clientes da CONTRATADA não se aplicarão à relação havida entre os ora CONTRATANTES, ficando o CONTRATANTE ciente que o valor praticado pela CONTRATADA em outros contratos pode divergir do que ora se pactua, não cabendo à CONTRATADA a padronização do valor do serviço a ser prestado em favor do CONTRATANTE para com outros contratos que foram ou serão firmados com terceiros.\n\nq) O presente contrato tem como objeto a locação de espaço para realização de eventos exclusivamente de natureza social, sendo vedada a sublocação do espaço pelo CONTRATANTE ou sua utilização para realização de festas abertas ao público em geral mediante comercialização de ingressos ou não, ficando desde já estabelecido que, caso o CONTRATANTE dê destinação diversa ao objeto da locação, o contrato será considerado rescindido por culpa exclusiva do mesmo, o qual deverá arcar com multa contratual no importe de 35% e todo e qualquer encargo financeiro decorrente de sua conduta perante a CONTRATADA ou a terceiros, sem prejuízo das demais cominações legais cabíveis.\n\nr) As partes se declaram cientes de que qualquer ato de difamação praticado em relação ao outro no que se refere ao objeto deste contrato será punível civil e criminalmente. Considerando que a CONTRATADA é locatária do espaço escolhido pelos CONTRATANTES para a realização de seu evento e que o referido contrato de locação prevê que, em caso de venda do imóvel por parte do locador/proprietário, a ora CONTRATADA terá de desocupá-lo em até 18 meses, os CONTRATANTES anuem desde já a possibilidade de antecipação de seu evento para antes da desocupação do imóvel ou, caso optem por manter a data inicialmente escolhida, terão de realizar seu evento em um dos demais espaços da CONTRATADA, quais serão ofertados em momento oportuno e conforme disponibilidade de agenda, não havendo a incidência de cláusula penal em desfavor de qualquer das partes na ocorrência destas hipóteses específicas.\n\n8) DO PAGAMENTO:\n\na) Para todos os casos, o saldo total deve encontrar-se quitado obrigatoriamente em no máximo 30 dias antes do evento, respeitando o prazo estipulado das parcelas. É obrigatório o pagamento de parcelas mensais consecutivas mínimas de R$ 600,00, até a quitação do contrato, iniciando no mês subsequente ao fechamento. Em caso de não quitação, o CONTRATADO possui a faculdade de não realizar o evento. Em caso de não cumprimento do prazo de pagamento das parcelas, ocorrerá juros de mora.\n\nb) Haja vista a necessidade de prevenir eventuais custos não calculados nos contratos de longo prazo ou até mesmo fazer frente a reajuste de preços no curso do contrato, para eventos que se realizarão após 05 meses de sua contratação será aplicada Taxa de Reajuste sobre o valor de alimentação, bebidas e taxa de serviço, nos seguintes patamares: até 12 meses: 12%; de 13 a 24 meses: 15%; de 25 a 36 meses: 20%; de 37 a 48 meses: 25%; de 49 a 60 meses: 30%; de 61 a 72 meses: 35%; de 73 a 84 meses: 40%; de 85 a 96 meses: 45%; superior a 96 meses: 50%. Parágrafo Primeiro: A taxa tem o intuito de garantir os valores do número de convidados disposto em contrato, para qualquer adicional, seguirá o valor do cardápio vigente no ato da contratação por aditivo contratual.\n\nc) Para casos de parcelamento do valor do contrato e aditivos contratuais, é cobrado juros de 1,29% a.m.. Parágrafo Primeiro: Os juros serão cobrados acima de 5x - parcelas mensais consecutivas, sendo a primeira subsequente à assinatura do contrato. Parágrafo Segundo: Para pagamentos que antecedem o evento será aplicado o juros de financiamento, e para casos de pagamento posterior ao evento (unicamente na modalidade do cartão de crédito) será aplicado juros composto. Parágrafo Terceiro: Para utilização do cartão de crédito, será sujeito a taxas de parcelamento que variam de 6,87% a 26,10%, dependendo da bandeira do cartão e do número de parcelas escolhido. Adicionalmente, incidirão juros de parcelamento de 1,29% ao mês + 8,9% por uso do cartão de crédito.\n\nd) Para cada cobrança de débitos oriundos deste contrato ou de despesas remanescentes do evento, a CONTRATADA poderá cobrar a taxa administrativa para cada processamento de pagamento realizado por meio de instrumentos de cobrança disponibilizados pela CONTRATADA, destinada a cobrir custos operacionais e administrativos relacionados à gestão e emissão do respectivo documento de cobrança, sendo os mesmos protestáveis no caso de não pagamento. O valor da taxa administrativa é de R$ 8,90 / und. ou parcela, em caso de boleto bancário. Em caso de pagamento com cartão de crédito, seguirá conforme previsto na cláusula 8, c). Passível de atualização de valores até a realização do evento. Parágrafo Único: Todo ajuste na programação de pagamento incidirá em uma nova cobrança da taxa. A programação de pagamento do contrato e aditivo contratual, não poderão ser unificados em um mesmo pagamento, tendo que ser obrigatoriamente separado. Formas de pagamento aprovadas: Boleto Bancário ou Cartão de Crédito (No cartão de crédito é aceito o parcelamento em no máximo de 18x - mediante inclusão de taxas pelo uso do cartão, conforme clasula anterior.). Pagamento via PIX é exclusivamente para a efetuação da entrada no momento da reunião de fechamento do contrato. Para o restante da programação financeira, a quitação deverá ser através de boleto bancário ou cartão de crédito.\n\ne) Em caso de aumento do número de pessoas na confirmação dos participantes do evento em relação ao contratado, a diferença de valores deverá ser paga através de boleto bancário em até 7 dias antes do evento, ou mediante cartão de crédito (com acréscimo da taxa de utilização do cartão e juros de parcelamento). Parágrafo Único: Tal disposição é aplicável aos valores devidos de buffet, bebidas na modalidade open bar e custo com a equipe.\n\nf) O contrato cujo pagamento não for acordado na data de sua assinatura, observará adimplementos mensais fixos, sendo a primeira parcela devida em 30 dias subsequentes à assinatura do contrato. Parágrafo Primeiro: O atraso no pagamento das parcelas em questão sujeitará a aplicação de juros de 1% ao mês e multa de 10%, bem como o protesto do título ou inscrição do CONTRATANTE no cadastro de inadimplentes. Parágrafo Segundo: O inadimplemento de 2 (duas) parcelas suspenderá a reserva da data para o evento, podendo o CONTRATADO comercializar a referida data, cabendo, após a regularização do débito o reagendamento do evento, conforme disponibilidade do CONTRATADO. Parágrafo Terceiro: Havendo o inadimplemento de 03 parcelas consecutivas, o CONTRATADO poderá considerar rescindido o contrato, procedendo o cancelamento do evento, sem prejuízo da aplicação da multa por descumprimento contratual prevista neste instrumento, sendo de total responsabilidade do CONTRATANTE o pagamento da multa contratual por quebra de contrato. Parágrafo Quarto: Os inadimplementos perpetrados pelo CONTRATANTE poderão ensejar a sua inscrição nos órgãos de proteção ao crédito, bem como poderão ser levados a protesto, inclusive as obrigações relativas a penalidades.\n\ng) Ao CONTRATANTE é possibilitada, posteriormente a sua assinatura, a redução de no máximo 20% do valor do contrato, somente mediante a aprovação do CONTRATADO. Entretanto, não será realizada restituição de valores ou abatimento do saldo devedor. Parágrafo Único: O crédito gerado pela redução do valor do contrato deverá ser revertido em serviços ou itens adicionais a serem prestados na data do evento, contudo, tais serviços devem ser contratados previamente via aditivo contratual, eis que tal saldo não pode ser revertido em consumo final.\n\nh) Toda reprogramação de toda forma de pagamento acordada, gera uma taxa de alteração fixa no valor de R$ 75,00 (setenta e cinco reais). Para reprogramação da forma de pagamento de apenas um mês, cobramos uma taxa para alteração de R$ 8,90 (oito e noventa centavos).\n\ni) Os contratos cuja forma de pagamento não for ajustada no ato de sua assinatura, terão o prazo de até 10 dias para tanto. Em caso não haver comunicação da forma de pagamento pelo CONTRATANTE, se adotará o modelo previstos no item 8) a), além do seguinte padrão: 10% do valor total a título de entrada e o saldo parcelado no número de meses que antecedem o evento, observando-se que, em 06 meses após a contratação, 30% do valor total do contrato esteja programado para pagamento, sendo devido o pagamento da primeira parcela em 30 dias após a assinatura do contrato.\n\nj) A pré-reserva de uma data para o evento, é temporária com validade de 48 horas e não anula a necessidade de uma formalização. A data do evento só será garantida a partir da formalização de aditivo contratual ou contrato. Para eventos sem definição de data, terá o prazo para definição de 4 meses após a assinatura do contrato. A data poderá ser escolhida apenas uma vez para eventos sem definição de data de imediato, recaindo à cláusula de alteração de data (cláusula 9.c) em caso de nova solicitação de alteração de data.\n\nk) Caso o evento ora contratado conte com a apresentação de músicos ou banda ou música ambiente, fica desde já estabelecido a taxa de R$ 1500,00 (Um mil e quinhentos reais) devida pelos CONTRATANTES a CONTRATADA a fim de que a mesma recolha o imposto devido junto ao ECAD, decorrente dos direitos autorais das músicas reproduzidas pelos músicos/banda no seu estabelecimento.\n\nl) As emissões das notas de prestação de serviços de alimentação e bebidas, quando contratado, equivalerão a 30% do valor total do contrato. Esse valor corresponderá ao montante registrado na nota de prestação de serviços emitida. O valor restante de 70% do contrato será destinado à locação de móveis e utensílios, conforme estabelecido na cláusula \"A\" do item \"5\" intitulado \"Dos Materiais\". De acordo com a Lei Complementar 116/03, as atividades de locação de máquinas, equipamentos, móveis, utensílios e quaisquer outros bens móveis não constituem fato gerador do Imposto Sobre Serviços de Qualquer Natureza (ISSQN). Portanto, tais atividades não estão sujeitas à emissão de Nota Fiscal de Serviços. As partes contratantes reconhecem e concordam que a divisão de valores descrita nesta cláusula tem como objetivo estabelecer a devida segregação entre os serviços de alimentação e bebidas prestados e a locação de móveis e utensílios fornecidos, a fim de cumprir as obrigações fiscais e regulatórias aplicáveis. Fica estipulado o prazo de até 3 dias úteis para a emissão da nota fiscal após a solicitação feita diretamente nos números oficiais do Pós Vendas.\n\nm) Todos os descontos concedidos no momento do fechamento deste contrato serão considerados válidos somente para este ato específico. Caso o CONTRATANTE deseje efetuar qualquer redução ou retirada dos produtos ou serviços contratados, o valor a ser considerado será o valor padrão vigente na data da assinatura do contrato, desconsiderando quaisquer descontos previamente concedidos.\n\nn) Após o vencimento de cada parcela, a concessão de descontos estabelecidos neste contrato permanecerá válida. No entanto, caso ocorra o atraso no pagamento de 2 parcelas consecutivas, a CONTRATADA reserva-se o direito de revogar os descontos concedidos. A partir desse ponto, o cálculo do valor devido será baseado no montante integral dos produtos ou serviços, conforme as tarifas padrão em vigor na data de assinatura deste contrato, e quaisquer descontos anteriores não serão mais aplicáveis. O departamento de cobranças da CONTRATADA será responsável por monitorar o número de parcelas vencidas e pela aplicação das devidas recuperações de desconto, quando necessário.\n\no) O cliente está ciente de que, em caso de inadimplência por um período superior a 10 dias, ocorrerá automaticamente o protesto por parte da empresa de cobrança, CNPJ 27.924.896/0001-51. O protesto será registrado no cartório correspondente à residência do cliente. A regularização do protesto deverá ser realizada pelo próprio cliente após o pagamento da dívida, mediante apresentação da carta de anuência fornecida pela empresa. O cliente será responsável pelas despesas cartoriais e emolumentos decorrentes do processo de baixa do protesto, e, nos casos de adimplência, quando a CONTRATADA achar necessário, poderá repassar recebíveis deste contrato ao CNPJ acima descrito ou a terceiros.\n\np) Em situações em que o pagamento for efetuado utilizando uma moeda que não o real brasileiro, será aplicado um acréscimo de 7%. Esse percentual está sujeito a alterações, podendo variar de acordo com as flutuações cambiais vigentes. O objetivo é ajustar o valor devido de acordo com as condições do mercado financeiro, garantindo uma equidade nas transações realizadas em diferentes moedas.\n\n9) DO DESCUMPRIMENTO:\n\na) As partes pactuam que o descumprimento contratual por parte do contratante ensejará a incidência de multa, no importe de 35% sobre o valor total contratado (contrato e aditivos contratuais). Parágrafo Único: Os descumprimentos contratuais ou ao Manual do Evento que não estiverem penalidades específicas, observarão o disposto nesta cláusula.\n\nb) Ocorrendo o cancelamento do evento, a partir da assinatura do presente contrato, após o devido abatimento do valor já pago, o saldo poderá ser ressarcido em até 12x. Parágrafo Primeiro: Ocorrendo o cancelamento do evento por parte do CONTRATANTE, fica o CONTRATADO desde já autorizado a proceder a retenção e/ou cobrança do valor correspondente a multa devida. Parágrafo Segundo: Ocorrendo o cancelamento do contratado por parte do CONTRATANTE, no período de 150 dias antes do evento, a cobrança será de 60% do valor total contratado. Parágrafo Terceiro: Havendo o cancelamento do evento por parte do CONTRATANTE, este será responsável pela indenização devida ao CONTRATADO pelos serviços já prestados pelo mesmo e seu pessoal, tais como: mão de obra da equipe de marketing, pré-vendas, vendas, pós-vendas, financeiro e equipe de operação do evento, sem prejuízo da incidência da multa prevista na Cláusula 9 item \"a\". Parágrafo Quarto: O CONTRATANTE fica ciente que havendo cancelamento do evento por sua iniciativa ou por sua culpa exclusiva, eventual contrato firmado pela CONTRATADA para com terceiros para atender o evento, tais como: pista de led, cadeiras de madeira, mesas, toalhas e demais itens decorativos, será, de mesma forma, cancelado, cabendo ao CONTRATANTE indenizar a CONTRATADA pelas multas contratuais que recaírem sobre si, decorrente do rompimento dos contratos firmados com tais fornecedores terceirizados. Parágrafo Quinto: A multa contratual terá a possibilidade de pagamento em no máximo 4 (quatro) parcelas consecutivas.\n\nc) Em caso de descumprimento do contrato no dia da realização do evento, fica o contratado autorizado a interrupção do evento e devidas medidas cabíveis.\n\n10) CONSIDERAÇÕES FINAIS:\n\na) A alteração da data do evento pelas partes em período superior a 45 dias após a assinatura do contrato, ensejará a aplicação da taxa de 20% sobre o valor total contratado, sem prejuízo da observância da disponibilidade de nova data pelo CONTRATADO. Parágrafo Primeiro: Ocorrendo a troca de data por parte do CONTRATANTE, no período de 180 dias antes do evento, a cobrança será de 50% do valor total contratado. Parágrafo Segundo: Caso a alteração de data não esteja nas mesmas condições da que contratada, ou seja uma alteração para véspera de feriado/feriado, será cobrado o valor adicional sobre a locação e a decoração.\n\nb) Do foro: As partes contratantes, de comum acordo, elegem o foro da cidade de Itapema - SC para dirimir qualquer dúvida ou omissões oriundas do presente contrato, em duas vias de igual teor e forma para um único fim e mesmo efeito legal.\n\nc) Com o pagamento da multa estipulada neste contrato, não caberão quaisquer outras indenizações.\n\nd) A data do evento poderá ser trocada por ambas as partes em até 45 dias após a assinatura do presente contrato, em apenas uma oportunidade, sem a incidência de taxa. Estando sujeita a disponibilidade de data do CONTRATADO, e respeitando o período acordado em contrato: Eventos de Segunda a Sexta (exceto feriados e vésperas) ou: Sábado, Domingo, feriados e vésperas de feriados. Estando ciente que em caso de alteração no dia de semana, ficará sujeito a diferença de valores a ser conversado diretamente com o Pós Vendas na data desta alteração.\n\ne) As partes firmam que as cláusulas e condições doravante descritas neste Contrato são de integral compreensão e alcance dos objetivos do presente negócio, pelo que nada poderá ser alegado, futuramente, pelo CONTRATANTE ou pela CONTRATADA sobre não ter tido conhecimento ou ter sido surpreendido\n\nf) O CONTRATANTE declara que as obrigações assumidas por ele neste instrumento estão de acordo com a sua capacidade econômico-financeira;\n\ng) O presente contrato permite o uso da imagem do CONTRATANTE pela CONTRATADA para fins promocionais e comerciais. Parágrafo Primeiro: O CONTRATANTE autoriza a CONTRATADA a utilizar sua imagem em fotos, vídeos, publicações em mídias sociais, anúncios impressos e outras formas de divulgação. Parágrafo Segundo: O CONTRATANTE garante que possui todos os direitos sobre sua imagem e libera a CONTRATADA de quaisquer responsabilidades decorrentes de reivindicações de terceiros. Parágrafo Terceiro: A utilização da imagem por período indeterminado a partir da data de assinatura deste contrato. Parágrafo Quarto: Fica estabelecido que a CONTRATADA tem a permissão para realizar visitação técnica ou agendada no espaço durante o evento por um período de até 10 minutos, para fins de conferência ou qualquer outra finalidade previamente acordada.\n\nh) Caso o presente contrato seja negociado sem juros, não excluirá a aplicação de juros de parcelamento nos aditivos contratuais conforme cláusula 8) c).\n\ni) Os valores negociados durante esta reunião são exclusivos para fechamento de contrato. Valores promocionais são exclusivos na feitura do contrato, após esta negociação contratual todos os produtos seguirão os preços vigentes e atualizados pelas tabelas comerciais do CONTRATADO - desconsiderando, portanto, valores negociados neste contrato para futuras contratações ou adições contratuais.\n\n\n\nPor estarem justos e contratados, firmam o presente instrumento em duas vias de igual teor e forma, na presença das testemunhas abaixo identificadas, para que produza seus efeitos legais.\n\n\nItapema, {{DATA_CONTRATACAO}}\n\n\n\n________________________________\nCONTRATADA\n{{CONTRATADA_NOME}}\n{{CONTRATADA_CNPJ}}\n\n\n\n________________________________\nCONTRATANTE\n{{CLIENTE_NOME}}\n{{CLIENTE_CPF_CNPJ}}\n\n\n\n________________________________\nVENDEDOR RESPONSÁVEL\n{{VENDEDOR}}\n\n\n\nContrato número: {{NUM_CONTRATO}}",
  "variaveis": [
    {
      "nome": "TIPO_EVENTO",
      "placeholder": "{{TIPO_EVENTO}}",
      "tipo": "evento",
      "obrigatorio": true,
      "valor_padrao": "Evento",
      "descricao": "Tipo do evento (ex: Casamento, 15 Anos, Corporativo)"
    },
    {
      "nome": "SERVICOS",
      "placeholder": "{{SERVICOS}}",
      "tipo": "evento",
      "obrigatorio": true,
      "valor_padrao": "Locação - Alimentação - Bebidas",
      "descricao": "Serviços contratados"
    },
    {
      "nome": "DATA_EVENTO",
      "placeholder": "{{DATA_EVENTO}}",
      "tipo": "data",
      "obrigatorio": true,
      "descricao": "Data de realização do evento"
    },
    {
      "nome": "NUM_CONVIDADOS",
      "placeholder": "{{NUM_CONVIDADOS}}",
      "tipo": "numero",
      "obrigatorio": true,
      "valor_padrao": "50",
      "descricao": "Número de convidados adultos"
    },
    {
      "nome": "ESPACO",
      "placeholder": "{{ESPACO}}",
      "tipo": "evento",
      "obrigatorio": true,
      "valor_padrao": "Esp. Cristal",
      "descricao": "Espaço onde será realizado o evento"
    },
    {
      "nome": "CLIENTE_NOME",
      "placeholder": "{{CLIENTE_NOME}}",
      "tipo": "cliente",
      "obrigatorio": true,
      "descricao": "Nome completo do cliente"
    },
    {
      "nome": "NUM_CONTRATO",
      "placeholder": "{{NUM_CONTRATO}}",
      "tipo": "texto",
      "obrigatorio": true,
      "descricao": "Número do contrato"
    },
    {
      "nome": "DATA_CONTRATACAO",
      "placeholder": "{{DATA_CONTRATACAO}}",
      "tipo": "data",
      "obrigatorio": true,
      "descricao": "Data de assinatura do contrato"
    },
    {
      "nome": "VENDEDOR",
      "placeholder": "{{VENDEDOR}}",
      "tipo": "texto",
      "obrigatorio": true,
      "descricao": "Nome do vendedor responsável"
    },
    {
      "nome": "CONTRATADA_NOME",
      "placeholder": "{{CONTRATADA_NOME}}",
      "tipo": "texto",
      "obrigatorio": true,
      "valor_padrao": "INDEX02 EVENTOS LTDA.",
      "descricao": "Nome da empresa contratada"
    },
    {
      "nome": "CONTRATADA_CNPJ",
      "placeholder": "{{CONTRATADA_CNPJ}}",
      "tipo": "texto",
      "obrigatorio": true,
      "valor_padrao": "30.969.797/0001-09",
      "descricao": "CNPJ da empresa contratada"
    },
    {
      "nome": "CLIENTE_CPF_CNPJ",
      "placeholder": "{{CLIENTE_CPF_CNPJ}}",
      "tipo": "cliente",
      "obrigatorio": true,
      "descricao": "CPF ou CNPJ do cliente"
    }
  ],
  "ativo": true
}